review_recommender/__init__.py
review_recommender/data_retriveal.py
review_recommender/inverted_files.py
review_recommender/ranker.py
review_recommender/scorer.py
review_recommender/tokenizer.py
review_recommender-1.0.3.dist-info/METADATA
review_recommender-1.0.3.dist-info/WHEEL
review_recommender-1.0.3.dist-info/entry_points.txt
review_recommender-1.0.3.dist-info/licenses/LICENSE
review_recommender-1.0.3.dist-info/RECORD
